{"comments":[],"workout_items":[{"id":174114005,"workout_id":39665967,"name":"Single Arm Row","info":"3 x 12 each side","result":"","is_circuit":false,"state":"missed","selected_exercises":[],"linked":false,"position":5,"assessment_id":null,"created_at":"2019-10-06T18:31:36.370Z","attachments":[],"exercise_id":396834,"request_video":false},{"id":174114006,"workout_id":39665967,"name":"1 Up 1 Down OH KB Walks","info":"3 x 6 lengths","result":"","is_circuit":false,"state":"missed","selected_exercises":[],"linked":true,"position":4,"assessment_id":null,"created_at":"2019-10-06T18:31:36.376Z","attachments":[],"exercise_id":null,"request_video":false},{"id":174114007,"workout_id":39665967,"name":"Straight Strength - Plate Lifts","info":"3 x 10","result":"","is_circuit":false,"state":"missed","selected_exercises":[],"linked":false,"position":7,"assessment_id":null,"created_at":"2019-10-06T18:31:36.380Z","attachments":[],"exercise_id":null,"request_video":false},{"id":174114008,"workout_id":39665967,"name":"Bent Strength - Bottom Up KB","info":"3x10 each arm","result":"","is_circuit":false,"state":"missed","selected_exercises":[],"linked":true,"position":6,"assessment_id":null,"created_at":"2019-10-06T18:31:36.384Z","attachments":[],"exercise_id":null,"request_video":false},{"id":174114009,"workout_id":39665967,"name":"Parallette Kick Through Slides","info":"3 x 10","result":"","is_circuit":false,"state":"missed","selected_exercises":[],"linked":false,"position":9,"assessment_id":null,"created_at":"2019-10-06T18:31:36.388Z","attachments":[],"exercise_id":null,"request_video":false},{"id":174114010,"workout_id":39665967,"name":"Rope Conditioning","info":"20s Alt into 20s Slam. 40s rest. x 5","result":"","is_circuit":false,"state":"missed","selected_exercises":[],"linked":false,"position":10,"assessment_id":null,"created_at":"2019-10-06T18:31:36.392Z","attachments":[],"exercise_id":null,"request_video":false},{"id":174114011,"workout_id":39665967,"name":"Chin Up Holds","info":"3 x 6 - 5s hold","result":"","is_circuit":false,"state":"missed","selected_exercises":[],"linked":true,"position":8,"assessment_id":null,"created_at":"2019-10-06T18:31:36.396Z","attachments":[],"exercise_id":null,"request_video":false},{"id":174114012,"workout_id":39665967,"name":"Posture / Mobility ","info":"Shoulder Rotations\nC1) Scap Shrugs 3 x 6\nC2) KB Windmills 3 x 6","result":"","is_circuit":true,"state":"missed","selected_exercises":[],"linked":false,"position":3,"assessment_id":null,"created_at":"2019-10-06T18:31:36.399Z","attachments":[],"exercise_id":null,"request_video":false},{"id":174114013,"workout_id":39665967,"name":"Proprioception Training","info":"Tennis Ball Catch -  2 mins","result":"","is_circuit":true,"state":"missed","selected_exercises":[],"linked":false,"position":2,"assessment_id":null,"created_at":"2019-10-06T18:31:36.403Z","attachments":[],"exercise_id":null,"request_video":false},{"id":174114014,"workout_id":39665967,"name":"Warm Up","info":"Rowing - 3 minutes","result":"","is_circuit":false,"state":"missed","selected_exercises":[],"linked":false,"position":1,"assessment_id":null,"created_at":"2019-10-06T18:31:36.406Z","attachments":[],"exercise_id":null,"request_video":false}],"workout":{"id":39665967,"due":"2019-10-11","short_description":"<p class='name-and-info'>A) Warm Up<br/>B) Proprioception Training<br/>C) Posture / Mobility <br/>D1) 1 Up 1 Down OH KB Walks<br/>D2) Single Arm Row<br/>E1) Bent Strength - Bottom Up KB<br/>E2) Straight Strength - Plate Lifts<br/>F1) Chin Up Holds<br/>F2) Parallette Kick Through Slides<br/>G) Rope Conditioning<br/></p>","created_at":"2019-10-06T18:31:36.312Z","updated_at":"2019-10-11T23:06:00.050Z","title":"","state":"missed","rest_day":false,"rest_day_instructions":"","warmup":null,"warmup_selected_exercises":[],"cooldown_selected_exercises":[],"cooldown":null,"position":null,"order":1,"uuid":"455bbd38-9306-46c0-9888-802b7dfdcb78","program_name":null,"hidden":false,"client_id":413684,"comment_ids":[],"note_id":null,"program_id":null,"workout_item_ids":[174114005,174114006,174114007,174114008,174114009,174114010,174114011,174114012,174114013,174114014]}}